russell/__init__.py
russell/cli.py
russell/content.py
russell/engine.py
russell/feed.py
russell/sitemap.py
russell-0.7.0.dist-info/METADATA
russell-0.7.0.dist-info/WHEEL
russell-0.7.0.dist-info/entry_points.txt
russell-0.7.0.dist-info/licenses/LICENSE
russell-0.7.0.dist-info/RECORD
