Metadata-Version: 2.4
Name: russell
Version: 0.7.0
Summary: A static HTML blog generator.
Project-URL: Homepage, https://github.com/anlutro/russell
Project-URL: Repository, https://github.com/anlutro/russell.git
Project-URL: Issues, https://github.com/anlutro/russell/issues
Author-email: Andreas Lutro <anlutro@gmail.com>
License-Expression: GPL-3.0-or-later
License-File: LICENSE
Keywords: blog,generator,html,static
Requires-Python: >=3.10
Requires-Dist: feedgen~=1.0
Requires-Dist: jinja2~=3.0
Requires-Dist: markdown~=3.3
Requires-Dist: python-dateutil~=2.6
Requires-Dist: python-slugify~=8.0
